nnmt/__init__.py
nnmt/_solvers.py
nnmt/binary.py
nnmt/input_output.py
nnmt/linear_stability.py
nnmt/network_properties.py
nnmt/spatial.py
nnmt/utils.py
nnmt/lif/__init__.py
nnmt/lif/_general.py
nnmt/lif/delta.py
nnmt/lif/exp.py
nnmt/models/__init__.py
nnmt/models/basic.py
nnmt/models/microcircuit.py
nnmt/models/network.py
nnmt/models/plain.py
nnmt-1.3.0.dist-info/LICENSE
nnmt-1.3.0.dist-info/METADATA
nnmt-1.3.0.dist-info/WHEEL
nnmt-1.3.0.dist-info/top_level.txt
nnmt-1.3.0.dist-info/RECORD
