Metadata-Version: 2.1
Name: nnmt
Version: 1.3.0
Summary: Neuronal Network Meanfield Toolbox
Home-page: https://github.com/INM-6/nnmt
Author: see docs/source/authors_and_contributors.rst
Author-email: m.layer@fz-juelich.de
License: GNU GPLv3
Requires-Python: >=3
License-File: LICENSE
Requires-Dist: setuptools (>=23.1.0)
Requires-Dist: numpy (>=1.8)
Requires-Dist: scipy (>=0.14)
Requires-Dist: Cython (>=0.20)
Requires-Dist: h5py (>=2.5)
Requires-Dist: matplotlib (>=2.0)
Requires-Dist: pint
Requires-Dist: pyyaml
Requires-Dist: requests
Requires-Dist: mpmath
Requires-Dist: decorator
Requires-Dist: pytest (>=5.4)
Requires-Dist: pytest-mock (>=3.1)
